{
  "timestamp": "2025-08-12T06:26:25Z",
  "if_tailwind_issues_persist": {
    "option_1": {
      "name": "Mantine",
      "description": "No Tailwind dependency, great for dashboards",
      "pros": ["No Tailwind", "Built-in dark theme", "Rich components"],
      "time_to_migrate": "30 minutes"
    },
    "option_2": {
      "name": "Chakra UI", 
      "description": "No Tailwind, emotion-based styling",
      "pros": ["No Tailwind", "Simple API", "Good performance"],
      "time_to_migrate": "45 minutes"
    },
    "option_3": {
      "name": "Pure CSS Modules",
      "description": "No framework, just CSS modules",
      "pros": ["No dependencies", "Full control", "No conflicts"],
      "time_to_migrate": "1 hour"
    },
    "option_4": {
      "name": "Material-UI (MUI)",
      "description": "Google Material Design, no Tailwind",
      "pros": ["Professional look", "No Tailwind", "Great docs"],
      "time_to_migrate": "45 minutes"
    }
  },
  "recommended_action": "test_current_setup_first"
}
